AlgorithmADTs/.DS_Store
AlgorithmADTs/AbstractDataTypes.py
AlgorithmADTs/GraphAlgorithms.py
AlgorithmADTs/__init__.py
algorithmadts-0.3.3.dist-info/METADATA
algorithmadts-0.3.3.dist-info/WHEEL
algorithmadts-0.3.3.dist-info/licenses/LICENSE
algorithmadts-0.3.3.dist-info/RECORD
