Metadata-Version: 2.1
Name: AlgorithmADTs
Version: 0.3.3
Summary: General purpose Abstract Data Types for Algorithmics
Author-email: Finlay <finlay3.141@gmail.com>
License-File: LICENSE
Classifier: License :: OSI Approved :: MIT License
Classifier: Operating System :: OS Independent
Classifier: Programming Language :: Python :: 3
Requires-Python: >=3.7
